MANIFEST.in
README.md
requirements.txt
setup.py
bin/grizzzly
src/grizzzly/__init__.py
src/grizzzly/__main__.py
src/grizzzly/cli.py
src/grizzzly/settings.py
src/grizzzly.egg-info/PKG-INFO
src/grizzzly.egg-info/SOURCES.txt
src/grizzzly.egg-info/dependency_links.txt
src/grizzzly.egg-info/entry_points.txt
src/grizzzly.egg-info/requires.txt
src/grizzzly.egg-info/top_level.txt
src/grizzzly/client/__init__.py
src/grizzzly/client/download.py
src/grizzzly/client/upload.py
src/grizzzly/server/__init__.py
src/grizzzly/server/api_download.py
src/grizzzly/server/api_hello.py
src/grizzzly/server/api_info.py
src/grizzzly/server/api_upload.py
src/grizzzly/server/models.py