Metadata-Version: 2.1
Name: grizzzly
Version: 0.7.0
Summary: This is your favorite data sharing library! Works great with pandas.
Home-page: UNKNOWN
License: UNKNOWN
Platform: UNKNOWN
